Metadata-Version: 1.0
Name: Gdistributions-dsnd
Version: 0.11
Summary: Gaussian distributions
Home-page: UNKNOWN
Author: UNKNOWN
Author-email: UNKNOWN
License: UNKNOWN
Platform: UNKNOWN
